esi_utils_comcat/__init__.py
esi_utils_comcat/query.py
esi_utils_comcat-0.0.4.dist-info/LICENSE.md
esi_utils_comcat-0.0.4.dist-info/METADATA
esi_utils_comcat-0.0.4.dist-info/WHEEL
esi_utils_comcat-0.0.4.dist-info/top_level.txt
esi_utils_comcat-0.0.4.dist-info/RECORD
