Metadata-Version: 2.1
Name: esi-utils-comcat
Version: 0.0.4
Summary: USGS ComCat/Geoserve convenience functionality
Author-email: Mike Hearne <mhearne@usgs.gov>
License: License
Keywords: losses,earthquake
Requires-Python: >=3.9
License-File: LICENSE.md
Requires-Dist: requests>=2.32.3
Requires-Dist: urllib3>=2.2.3
Provides-Extra: dev
Requires-Dist: build>=0.9.0; extra == "dev"
Requires-Dist: black>=22.12.0; extra == "dev"
Requires-Dist: flake8>=6.0.0; extra == "dev"
Requires-Dist: ipython>=8.8.0; extra == "dev"
Requires-Dist: notebook>=6.5.2; extra == "dev"
Requires-Dist: twine>=4.0.2; extra == "dev"
Provides-Extra: test
Requires-Dist: pytest>=7.2.0; extra == "test"
Requires-Dist: pytest-cov>=4.0.0; extra == "test"
Requires-Dist: vcrpy>=6.0.2; extra == "test"
Provides-Extra: build
Requires-Dist: build; extra == "build"
Requires-Dist: twine; extra == "build"
